.gitignore
LICENSE
README.md
pyproject.toml
requirements.txt
setup.py
.github/ISSUE_TEMPLATE/bug_report.md
.github/ISSUE_TEMPLATE/feature_request.md
.github/workflows/ci.yml
pylibagent/__init__.py
pylibagent/agent.py
pylibagent/check.py
pylibagent/exceptions.py
pylibagent/logger.py
pylibagent/severity.py
pylibagent/version.py
pylibagent.egg-info/PKG-INFO
pylibagent.egg-info/SOURCES.txt
pylibagent.egg-info/dependency_links.txt
pylibagent.egg-info/requires.txt
pylibagent.egg-info/top_level.txt