Metadata-Version: 2.1
Name: pylibagent
Version: 1.0.2
Summary: Library for building InfraSonar agents
Home-page: https://github.com/infrasonar/python-libagent
Download-URL: https://github.com/infrasonar/python-libagent/tarball/v1.0.2
Author: Cesbit
Author-email: info@cesbit.com
Keywords: monitoring,infrasonar,agent
Classifier: Intended Audience :: Developers
Classifier: Operating System :: OS Independent
Classifier: Programming Language :: Python :: 3.9
Classifier: Programming Language :: Python :: 3.10
Classifier: Programming Language :: Python :: 3.11
Classifier: Programming Language :: Python :: 3.12
Classifier: Programming Language :: Python :: 3 :: Only
Classifier: Topic :: Software Development :: Libraries :: Python Modules
Classifier: Topic :: Text Processing :: Linguistic
License-File: LICENSE
Requires-Dist: aiohttp
Requires-Dist: colorlog
Requires-Dist: msgpack
Requires-Dist: setproctitle
